symconstraints/__init__.py
symconstraints/__version__.py
symconstraints/constraints.py
symconstraints/mapping.py
symconstraints/operation.py
symconstraints/pandas.py
symconstraints-0.0.1.dist-info/WHEEL
symconstraints-0.0.1.dist-info/METADATA
symconstraints-0.0.1.dist-info/RECORD
