Metadata-Version: 2.1
Name: symconstraints
Version: 0.0.1
Summary: 
Keywords: 
Author-email: Abdelrahman Abdelrahman <me@abogic.al>
Requires-Python: >=3.10
Classifier: Development Status :: 4 - Beta
Classifier: Programming Language :: Python
Classifier: Programming Language :: Python :: 3.10
Classifier: Programming Language :: Python :: 3.11
Classifier: Programming Language :: Python :: 3.12
Classifier: Programming Language :: Python :: Implementation :: CPython
Classifier: Programming Language :: Python :: Implementation :: PyPy
Classifier: License :: OSI Approved :: MIT License
Requires-Dist: sympy>=1.12,<2
Requires-Dist: cairosvg ; extra == "docs"
Requires-Dist: mkdocs-material ; extra == "docs"
Requires-Dist: mkdocstrings[python] ; extra == "docs"
Requires-Dist: pandas ; extra == "test"
Requires-Dist: numpy ; extra == "test"
Requires-Dist: pytest ; extra == "test"
Requires-Dist: pytest-cov ; extra == "test"
Requires-Dist: ipdb ; extra == "test"
Project-URL: Documentation, https://github.com/Abogical/symconstraints#readme
Project-URL: Issues, https://github.com/Abogical/symconstraints/issues
Project-URL: Source, https://github.com/Abogical/symconstraints
Provides-Extra: docs
Provides-Extra: test
